{"label": "0", "color": null, "tstamp": 1.0, "dist": 0.0, "transferred": 0, "id": 0, "children": [{"label": "1", "color": null, "tstamp": 0.8677957433228658, "dist": 0.1322042566771342, "transferred": 0, "sibling_nr": 0, "id": 1, "children": [{"label": "2", "color": null, "tstamp": 0.6006543252623555, "dist": 0.2671414180605103, "transferred": 0, "sibling_nr": 0, "id": 2, "children": [{"label": "4", "color": null, "tstamp": 0.3216680143569366, "dist": 0.2789863109054189, "transferred": 0, "sibling_nr": 0, "id": 4, "children": [{"label": "8", "color": null, "tstamp": 0.0, "dist": 0.3216680143569366, "transferred": 0, "sibling_nr": 0, "id": 8}, {"label": "9", "color": null, "tstamp": 0.11676337043547604, "dist": 0.20490464392146057, "transferred": 0, "sibling_nr": 1, "id": 9, "children": [{"label": "10", "color": null, "tstamp": 0.10503601827178187, "dist": 0.011727352163694166, "transferred": 0, "sibling_nr": 0, "id": 10, "children": [{"label": "18", "color": null, "tstamp": 0.0, "dist": 0.10503601827178187, "transferred": 0, "sibling_nr": 0, "id": 18}, {"label": "19", "color": null, "tstamp": 0.0, "dist": 0.10503601827178187, "transferred": 0, "sibling_nr": 1, "id": 19}]}, {"label": "11", "color": null, "tstamp": 0.058264889481502345, "dist": 0.05849848095397369, "transferred": 0, "sibling_nr": 1, "id": 11, "children": [{"label": "12", "color": null, "tstamp": 0.0, "dist": 0.058264889481502345, "transferred": 0, "sibling_nr": 0, "id": 12}, {"label": "13", "color": null, "tstamp": 0.0016719421751048352, "dist": 0.05659294730639751, "transferred": 0, "sibling_nr": 1, "id": 13, "children": [{"label": "14", "color": null, "tstamp": 0.0, "dist": 0.0016719421751048352, "transferred": 0, "sibling_nr": 0, "id": 14}, {"label": "15", "color": null, "tstamp": 0.0, "dist": 0.0016719421751048352, "transferred": 0, "sibling_nr": 1, "id": 15}]}]}]}]}, {"label": "5", "color": null, "tstamp": 0.4130441004656023, "dist": 0.1876102247967532, "transferred": 0, "sibling_nr": 1, "id": 5, "children": [{"label": "6", "color": null, "tstamp": 0.0, "dist": 0.4130441004656023, "transferred": 0, "sibling_nr": 0, "id": 6}, {"label": "7", "color": null, "tstamp": 0.0, "dist": 0.4130441004656023, "transferred": 0, "sibling_nr": 1, "id": 7}]}]}, {"label": "3", "color": null, "tstamp": 0.4154294881792615, "dist": 0.4523662551436043, "transferred": 0, "sibling_nr": 1, "id": 3, "children": [{"label": "16", "color": null, "tstamp": 0.0, "dist": 0.4154294881792615, "transferred": 0, "sibling_nr": 0, "id": 16}, {"label": "17", "color": null, "tstamp": 0.0, "dist": 0.4154294881792615, "transferred": 0, "sibling_nr": 1, "id": 17}]}]}]}