{"label": "0", "color": null, "tstamp": 1.0, "dist": 0.0, "transferred": 0, "id": 0, "children": [{"label": "1", "color": null, "tstamp": 0.8807041375442329, "dist": 0.11929586245576707, "transferred": 0, "sibling_nr": 0, "id": 1, "children": [{"label": "2", "color": null, "tstamp": 0.6182379232375975, "dist": 0.2624662143066354, "transferred": 0, "sibling_nr": 0, "id": 2, "children": [{"label": "4", "color": null, "tstamp": 0.3594623767126183, "dist": 0.2587755465249792, "transferred": 0, "sibling_nr": 0, "id": 4, "children": [{"label": "8", "color": null, "tstamp": 0.0, "dist": 0.3594623767126183, "transferred": 0, "sibling_nr": 0, "id": 8}, {"label": "9", "color": null, "tstamp": 0.30984790316989075, "dist": 0.04961447354272758, "transferred": 0, "sibling_nr": 1, "id": 9, "children": [{"label": "10", "color": null, "tstamp": 0.2926457822521061, "dist": 0.01720212091778467, "transferred": 0, "sibling_nr": 0, "id": 10, "children": [{"label": "18", "color": null, "tstamp": 0.0, "dist": 0.2926457822521061, "transferred": 0, "sibling_nr": 0, "id": 18}, {"label": "19", "color": null, "tstamp": 0.0, "dist": 0.2926457822521061, "transferred": 0, "sibling_nr": 1, "id": 19}]}, {"label": "11", "color": null, "tstamp": 0.1082531185021143, "dist": 0.20159478466777644, "transferred": 0, "sibling_nr": 1, "id": 11, "children": [{"label": "14", "color": null, "tstamp": 0.0, "dist": 0.1082531185021143, "transferred": 0, "sibling_nr": 0, "id": 14}, {"label": "15", "color": null, "tstamp": 0.03979756050594607, "dist": 0.06845555799616823, "transferred": 0, "sibling_nr": 1, "id": 15, "children": [{"label": "16", "color": null, "tstamp": 0.0, "dist": 0.03979756050594607, "transferred": 0, "sibling_nr": 0, "id": 16}, {"label": "17", "color": null, "tstamp": 0.0, "dist": 0.03979756050594607, "transferred": 0, "sibling_nr": 1, "id": 17}]}]}]}]}, {"label": "5", "color": null, "tstamp": 0.3190113947893078, "dist": 0.29922652844828973, "transferred": 0, "sibling_nr": 1, "id": 5, "children": [{"label": "6", "color": null, "tstamp": 0.0, "dist": 0.3190113947893078, "transferred": 0, "sibling_nr": 0, "id": 6}, {"label": "7", "color": null, "tstamp": 0.0, "dist": 0.3190113947893078, "transferred": 0, "sibling_nr": 1, "id": 7}]}]}, {"label": "3", "color": null, "tstamp": 0.7374103210672458, "dist": 0.14329381647698713, "transferred": 0, "sibling_nr": 1, "id": 3, "children": [{"label": "12", "color": null, "tstamp": 0.0, "dist": 0.7374103210672458, "transferred": 0, "sibling_nr": 0, "id": 12}, {"label": "13", "color": null, "tstamp": 0.0, "dist": 0.7374103210672458, "transferred": 0, "sibling_nr": 1, "id": 13}]}]}]}