{"label": "0", "color": null, "tstamp": 1.0, "dist": 0.0, "transferred": 0, "id": 0, "children": [{"label": "1", "color": null, "tstamp": 0.39056044796234246, "dist": 0.6094395520376575, "transferred": 0, "sibling_nr": 0, "id": 1, "children": [{"label": "2", "color": null, "tstamp": 0.01437723266201817, "dist": 0.3761832153003243, "transferred": 0, "sibling_nr": 0, "id": 2, "children": [{"label": "4", "color": null, "tstamp": 0.0, "dist": 0.01437723266201817, "transferred": 0, "sibling_nr": 0, "id": 4}, {"label": "5", "color": null, "tstamp": 0.003721274567570791, "dist": 0.010655958094447379, "transferred": 0, "sibling_nr": 1, "id": 5, "children": [{"label": "6", "color": null, "tstamp": 0.0, "dist": 0.003721274567570791, "transferred": 0, "sibling_nr": 0, "id": 6}, {"label": "7", "color": null, "tstamp": 0.002631070978494058, "dist": 0.0010902035890767328, "transferred": 0, "sibling_nr": 1, "id": 7, "children": [{"label": "8", "color": null, "tstamp": 0.0, "dist": 0.002631070978494058, "transferred": 0, "sibling_nr": 0, "id": 8}, {"label": "9", "color": null, "tstamp": 0.0010923424218504266, "dist": 0.0015387285566436314, "transferred": 0, "sibling_nr": 1, "id": 9, "children": [{"label": "10", "color": null, "tstamp": 0.0, "dist": 0.0010923424218504266, "transferred": 0, "sibling_nr": 0, "id": 10}, {"label": "11", "color": null, "tstamp": 0.0005656280805216454, "dist": 0.0005267143413287812, "transferred": 0, "sibling_nr": 1, "id": 11, "children": [{"label": "14", "color": null, "tstamp": 0.00010038904826177869, "dist": 0.00046523903225986676, "transferred": 0, "sibling_nr": 0, "id": 14, "children": [{"label": "18", "color": null, "tstamp": 0.0, "dist": 0.00010038904826177869, "transferred": 0, "sibling_nr": 0, "id": 18}, {"label": "19", "color": null, "tstamp": 0.0, "dist": 0.00010038904826177869, "transferred": 0, "sibling_nr": 1, "id": 19}]}, {"label": "15", "color": null, "tstamp": 0.0005350987259017073, "dist": 3.052935461993818e-05, "transferred": 0, "sibling_nr": 1, "id": 15, "children": [{"label": "16", "color": null, "tstamp": 0.0, "dist": 0.0005350987259017073, "transferred": 0, "sibling_nr": 0, "id": 16}, {"label": "17", "color": null, "tstamp": 0.0, "dist": 0.0005350987259017073, "transferred": 0, "sibling_nr": 1, "id": 17}]}]}]}]}]}]}, {"label": "3", "color": null, "tstamp": 0.3606005854307158, "dist": 0.029959862531626635, "transferred": 0, "sibling_nr": 1, "id": 3, "children": [{"label": "12", "color": null, "tstamp": 0.0, "dist": 0.3606005854307158, "transferred": 0, "sibling_nr": 0, "id": 12}, {"label": "13", "color": null, "tstamp": 0.0, "dist": 0.3606005854307158, "transferred": 0, "sibling_nr": 1, "id": 13}]}]}]}