{"label": "0", "color": null, "tstamp": 1.0, "dist": 0.0, "transferred": 0, "id": 0, "children": [{"label": "1", "color": null, "tstamp": 0.45520053381775194, "dist": 0.5447994661822481, "transferred": 0, "sibling_nr": 0, "id": 1, "children": [{"label": "2", "color": null, "tstamp": 0.19817843924160805, "dist": 0.2570220945761439, "transferred": 0, "sibling_nr": 0, "id": 2, "children": [{"label": "4", "color": null, "tstamp": 0.0, "dist": 0.19817843924160805, "transferred": 0, "sibling_nr": 0, "id": 4}, {"label": "5", "color": null, "tstamp": 0.05259395070329935, "dist": 0.1455844885383087, "transferred": 0, "sibling_nr": 1, "id": 5, "children": [{"label": "6", "color": null, "tstamp": 0.0146829231322416, "dist": 0.03791102757105775, "transferred": 0, "sibling_nr": 0, "id": 6, "children": [{"label": "14", "color": null, "tstamp": 0.0, "dist": 0.0146829231322416, "transferred": 0, "sibling_nr": 0, "id": 14}, {"label": "15", "color": null, "tstamp": 0.011691189940208685, "dist": 0.0029917331920329155, "transferred": 0, "sibling_nr": 1, "id": 15, "children": [{"label": "16", "color": null, "tstamp": 0.0, "dist": 0.011691189940208685, "transferred": 0, "sibling_nr": 0, "id": 16}, {"label": "17", "color": null, "tstamp": 0.0058462316734099965, "dist": 0.005844958266798688, "transferred": 0, "sibling_nr": 1, "id": 17, "children": [{"label": "18", "color": null, "tstamp": 0.0, "dist": 0.0058462316734099965, "transferred": 0, "sibling_nr": 0, "id": 18}, {"label": "19", "color": null, "tstamp": 0.0, "dist": 0.0058462316734099965, "transferred": 0, "sibling_nr": 1, "id": 19}]}]}]}, {"label": "7", "color": null, "tstamp": 0.0, "dist": 0.05259395070329935, "transferred": 0, "sibling_nr": 1, "id": 7}]}]}, {"label": "3", "color": null, "tstamp": 0.44057912095295554, "dist": 0.014621412864796401, "transferred": 0, "sibling_nr": 1, "id": 3, "children": [{"label": "8", "color": null, "tstamp": 0.0, "dist": 0.44057912095295554, "transferred": 0, "sibling_nr": 0, "id": 8}, {"label": "9", "color": null, "tstamp": 0.006747416610640043, "dist": 0.4338317043423155, "transferred": 0, "sibling_nr": 1, "id": 9, "children": [{"label": "10", "color": null, "tstamp": 0.0, "dist": 0.006747416610640043, "transferred": 0, "sibling_nr": 0, "id": 10}, {"label": "11", "color": null, "tstamp": 0.005917906632871404, "dist": 0.0008295099777686386, "transferred": 0, "sibling_nr": 1, "id": 11, "children": [{"label": "12", "color": null, "tstamp": 0.0, "dist": 0.005917906632871404, "transferred": 0, "sibling_nr": 0, "id": 12}, {"label": "13", "color": null, "tstamp": 0.0, "dist": 0.005917906632871404, "transferred": 0, "sibling_nr": 1, "id": 13}]}]}]}]}]}