{"label": "0", "color": null, "tstamp": 1.0, "dist": 0.0, "transferred": 0, "id": 0, "children": [{"label": "1", "color": null, "tstamp": 0.027086529424272143, "dist": 0.9729134705757279, "transferred": 0, "sibling_nr": 0, "id": 1, "children": [{"label": "2", "color": null, "tstamp": 0.0, "dist": 0.027086529424272143, "transferred": 0, "sibling_nr": 0, "id": 2}, {"label": "3", "color": null, "tstamp": 0.026593675610693018, "dist": 0.0004928538135791256, "transferred": 0, "sibling_nr": 1, "id": 3, "children": [{"label": "4", "color": null, "tstamp": 0.0, "dist": 0.026593675610693018, "transferred": 0, "sibling_nr": 0, "id": 4}, {"label": "5", "color": null, "tstamp": 0.008467536798269953, "dist": 0.018126138812423066, "transferred": 0, "sibling_nr": 1, "id": 5, "children": [{"label": "6", "color": null, "tstamp": 0.0, "dist": 0.008467536798269953, "transferred": 0, "sibling_nr": 0, "id": 6}, {"label": "7", "color": null, "tstamp": 0.006360518489192179, "dist": 0.0021070183090777742, "transferred": 0, "sibling_nr": 1, "id": 7, "children": [{"label": "8", "color": null, "tstamp": 0.0, "dist": 0.006360518489192179, "transferred": 0, "sibling_nr": 0, "id": 8}, {"label": "9", "color": null, "tstamp": 0.005432119067649469, "dist": 0.0009283994215427095, "transferred": 0, "sibling_nr": 1, "id": 9, "children": [{"label": "10", "color": null, "tstamp": 0.003652518465386766, "dist": 0.0017796006022627034, "transferred": 0, "sibling_nr": 0, "id": 10, "children": [{"label": "14", "color": null, "tstamp": 0.0, "dist": 0.003652518465386766, "transferred": 0, "sibling_nr": 0, "id": 14}, {"label": "15", "color": null, "tstamp": 0.002166242171498821, "dist": 0.0014862762938879451, "transferred": 0, "sibling_nr": 1, "id": 15, "children": [{"label": "16", "color": null, "tstamp": 0.0, "dist": 0.002166242171498821, "transferred": 0, "sibling_nr": 0, "id": 16}, {"label": "17", "color": null, "tstamp": 0.0, "dist": 0.002166242171498821, "transferred": 0, "sibling_nr": 1, "id": 17}]}]}, {"label": "11", "color": null, "tstamp": 0.0007023676286358903, "dist": 0.004729751439013579, "transferred": 0, "sibling_nr": 1, "id": 11, "children": [{"label": "12", "color": null, "tstamp": 0.00036396699057630107, "dist": 0.0003384006380595892, "transferred": 0, "sibling_nr": 0, "id": 12, "children": [{"label": "18", "color": null, "tstamp": 0.0, "dist": 0.00036396699057630107, "transferred": 0, "sibling_nr": 0, "id": 18}, {"label": "19", "color": null, "tstamp": 0.0, "dist": 0.00036396699057630107, "transferred": 0, "sibling_nr": 1, "id": 19}]}, {"label": "13", "color": null, "tstamp": 0.0, "dist": 0.0007023676286358903, "transferred": 0, "sibling_nr": 1, "id": 13}]}]}]}]}]}]}]}