{"label": "0", "color": null, "tstamp": 1.0, "dist": 0.0, "transferred": 0, "id": 0, "children": [{"label": "1", "color": null, "tstamp": 0.40484838113319865, "dist": 0.5951516188668013, "transferred": 0, "sibling_nr": 0, "id": 1, "children": [{"label": "2", "color": null, "tstamp": 0.3291708556507314, "dist": 0.07567752548246726, "transferred": 0, "sibling_nr": 0, "id": 2, "children": [{"label": "4", "color": null, "tstamp": 0.0, "dist": 0.3291708556507314, "transferred": 0, "sibling_nr": 0, "id": 4}, {"label": "5", "color": null, "tstamp": 0.24031865210897443, "dist": 0.08885220354175696, "transferred": 0, "sibling_nr": 1, "id": 5, "children": [{"label": "6", "color": null, "tstamp": 0.16544924920130002, "dist": 0.07486940290767441, "transferred": 0, "sibling_nr": 0, "id": 6, "children": [{"label": "12", "color": null, "tstamp": 0.0, "dist": 0.16544924920130002, "transferred": 0, "sibling_nr": 0, "id": 12}, {"label": "13", "color": null, "tstamp": 0.09209466403869651, "dist": 0.07335458516260351, "transferred": 0, "sibling_nr": 1, "id": 13, "children": [{"label": "14", "color": null, "tstamp": 0.07811427321675993, "dist": 0.013980390821936584, "transferred": 0, "sibling_nr": 0, "id": 14, "children": [{"label": "18", "color": null, "tstamp": 0.0, "dist": 0.07811427321675993, "transferred": 0, "sibling_nr": 0, "id": 18}, {"label": "19", "color": null, "tstamp": 0.0, "dist": 0.07811427321675993, "transferred": 0, "sibling_nr": 1, "id": 19}]}, {"label": "15", "color": null, "tstamp": 0.011147729377141632, "dist": 0.08094693466155488, "transferred": 0, "sibling_nr": 1, "id": 15, "children": [{"label": "16", "color": null, "tstamp": 0.0, "dist": 0.011147729377141632, "transferred": 0, "sibling_nr": 0, "id": 16}, {"label": "17", "color": null, "tstamp": 0.0, "dist": 0.011147729377141632, "transferred": 0, "sibling_nr": 1, "id": 17}]}]}]}, {"label": "7", "color": null, "tstamp": 0.12535261625647973, "dist": 0.11496603585249471, "transferred": 0, "sibling_nr": 1, "id": 7, "children": [{"label": "8", "color": null, "tstamp": 0.0, "dist": 0.12535261625647973, "transferred": 0, "sibling_nr": 0, "id": 8}, {"label": "9", "color": null, "tstamp": 0.09337546062942607, "dist": 0.03197715562705365, "transferred": 0, "sibling_nr": 1, "id": 9, "children": [{"label": "10", "color": null, "tstamp": 0.0, "dist": 0.09337546062942607, "transferred": 0, "sibling_nr": 0, "id": 10}, {"label": "11", "color": null, "tstamp": 0.0, "dist": 0.09337546062942607, "transferred": 0, "sibling_nr": 1, "id": 11}]}]}]}]}, {"label": "3", "color": null, "tstamp": 0.0, "dist": 0.40484838113319865, "transferred": 0, "sibling_nr": 1, "id": 3}]}]}